hudu_api_d2/__init__.py
hudu_api_d2/getAssetsById.py
hudu_api_d2-0.0.1.dist-info/LICENSE
hudu_api_d2-0.0.1.dist-info/METADATA
hudu_api_d2-0.0.1.dist-info/WHEEL
hudu_api_d2-0.0.1.dist-info/top_level.txt
hudu_api_d2-0.0.1.dist-info/RECORD
